calculator_mcc/__init__.py
calculator_mcc/calculator_mcc.py
calculator_mcc-0.1.4.dist-info/LICENSE
calculator_mcc-0.1.4.dist-info/WHEEL
calculator_mcc-0.1.4.dist-info/METADATA
calculator_mcc-0.1.4.dist-info/RECORD
