Metadata-Version: 2.1
Name: calculator_mcc
Version: 0.1.4
Summary: Calculator module
Author-email: Mei-Chieh Chien <meichieh.chien@gmail.com>
Classifier: License :: OSI Approved :: MIT License
